kolibri_sentry_plugin/__init__.py
kolibri_sentry_plugin/kolibri_plugin.py
kolibri_sentry_plugin/options.py
kolibri_sentry_plugin/settings.py
kolibri_sentry_plugin/build/kolibri_sentry_plugin.main_stats.json
kolibri_sentry_plugin/static/kolibri_sentry_plugin.main/kolibri_sentry_plugin.main-0.2.0.js
kolibri_sentry_plugin/static/kolibri_sentry_plugin.main/kolibri_sentry_plugin.main-0.2.0.js.map
kolibri_sentry_plugin-0.2.0.dist-info/AUTHORS.rst
kolibri_sentry_plugin-0.2.0.dist-info/LICENSE
kolibri_sentry_plugin-0.2.0.dist-info/METADATA
kolibri_sentry_plugin-0.2.0.dist-info/WHEEL
kolibri_sentry_plugin-0.2.0.dist-info/entry_points.txt
kolibri_sentry_plugin-0.2.0.dist-info/top_level.txt
kolibri_sentry_plugin-0.2.0.dist-info/RECORD
